py_framework/__init__.py
py_framework/py_application.py
py_framework/py_constants.py
py_framework/agent/__init__.py
py_framework/config/__init__.py
py_framework/config/app_environment.py
py_framework/config/application_config_resolver.py
py_framework/config/base_config_resolver.py
py_framework/config/bootstrap_config_resolver.py
py_framework/config/env_config_resolver.py
py_framework/context/__init__.py
py_framework/context/application_context.py
py_framework/data/__init__.py
py_framework/data/jdbc/__init__.py
py_framework/data/jdbc/base_jdbc_template.py
py_framework/data/jdbc/clickhouse_jdbc_template.py
py_framework/data/jdbc/jdbc_template.py
py_framework/data/jdbc/mysql_jdbc_template.py
py_framework/data/jdbc/sql_formatter.py
py_framework/data/shaper/__init__.py
py_framework/data/shaper/constants.py
py_framework/data/shaper/data_shaper.py
py_framework/data/shaper/errors.py
py_framework/data/shaper/schema/__init__.py
py_framework/data/shaper/tables/__init__.py
py_framework/data/shaper/tables/csv.py
py_framework/data/shaper/tables/json.py
py_framework/data/shaper/tables/table.py
py_framework/data/shaper/tables/types.py
py_framework/data/shaper/tables/store/__init__.py
py_framework/data/shaper/tables/store/disk_cache_table_store.py
py_framework/data/shaper/tables/store/in_memory_table_store.py
py_framework/data/shaper/tables/store/table_store.py
py_framework/data/shaper/utils/__init__.py
py_framework/data/shaper/utils/parallelization/__init__.py
py_framework/data/shaper/utils/parallelization/derive_from_rows.py
py_framework/data/shaper/utils/parallelization/derive_from_rows_asyncio.py
py_framework/data/shaper/utils/parallelization/derive_from_rows_asyncio_threads.py
py_framework/data/shaper/utils/parallelization/derive_from_rows_base.py
py_framework/data/shaper/utils/parallelization/types.py
py_framework/data/shaper/utils/progress/__init__.py
py_framework/data/shaper/utils/progress/progress_callback.py
py_framework/data/shaper/utils/progress/progress_iterable.py
py_rtf_framework-2.0.7.dist-info/LICENSE
py_rtf_framework-2.0.7.dist-info/METADATA
py_rtf_framework-2.0.7.dist-info/WHEEL
py_rtf_framework-2.0.7.dist-info/top_level.txt
py_rtf_framework-2.0.7.dist-info/RECORD
