Metadata-Version: 2.1
Name: py_rtf_framework
Version: 2.0.7
Home-page: 
Author: liupeng
Author-email: 895876294@qq.com
License: Apache
Classifier: License :: OSI Approved :: Apache Software License
Classifier: Natural Language :: English
Classifier: Operating System :: OS Independent
Classifier: Programming Language :: Python
Classifier: Programming Language :: Python :: 3.12
Classifier: Topic :: Software Development :: Libraries :: Python Modules
Requires-Python: >=3.12
License-File: LICENSE
Requires-Dist: fsspec==2024.10.0
Requires-Dist: polars==1.16.0
Requires-Dist: pydantic==2.10.4
Requires-Dist: aiofiles==24.1.0
Requires-Dist: aiolimiter==1.2.1
Requires-Dist: tqdm==4.67.1
Requires-Dist: cachetools==5.5.0
Requires-Dist: diskcache==5.6.3
Requires-Dist: tenacity==9.0.0
Requires-Dist: apscheduler==3.11.0
Requires-Dist: pandas==2.2.3
